pyo3_sf_demo_greeter-0.3.0.dist-info/METADATA
pyo3_sf_demo_greeter-0.3.0.dist-info/WHEEL
pyo3_sf_demo_greeter-0.3.0.dist-info/entry_points.txt
pyo3_sf_demo_greeter/__init__.py
pyo3_sf_demo_greeter/_core.abi3.so
pyo3_sf_demo_greeter/_core.pyi
pyo3_sf_demo_greeter/py.typed
pyo3_sf_demo_greeter-0.3.0.dist-info/RECORD
