Metadata-Version: 2.4
Name: pyo3-sf-demo-greeter
Version: 0.3.0
Summary: A demo PyO3 Rust extension for Snowflake UDFs
Author-email: Masa Fukui <masahiro.m.fukui@gmail.com>
Requires-Python: >=3.11
